layout_prompter/__init__.py
layout_prompter/layout_prompter.py
layout_prompter/settings.py
layout_prompter/typehints.py
layout_prompter/datasets/__init__.py
layout_prompter/datasets/poster_layout.py
layout_prompter/datasets/rico.py
layout_prompter/models/__init__.py
layout_prompter/models/layout_data.py
layout_prompter/models/serialized_data.py
layout_prompter/modules/__init__.py
layout_prompter/modules/rankers/__init__.py
layout_prompter/modules/rankers/base.py
layout_prompter/modules/rankers/layout_prompter.py
layout_prompter/modules/selectors/__init__.py
layout_prompter/modules/selectors/base.py
layout_prompter/modules/selectors/content_aware_selector.py
layout_prompter/modules/serializers/__init__.py
layout_prompter/modules/serializers/base.py
layout_prompter/modules/serializers/content_aware_serializer.py
layout_prompter/modules/serializers/gen_type_serializer.py
layout_prompter/preprocessors/__init__.py
layout_prompter/preprocessors/base.py
layout_prompter/preprocessors/completion_processor.py
layout_prompter/preprocessors/content_aware_processor.py
layout_prompter/preprocessors/gen_relation_processor.py
layout_prompter/preprocessors/gen_type_processor.py
layout_prompter/preprocessors/gen_type_size_processor.py
layout_prompter/preprocessors/refinement_processor.py
layout_prompter/preprocessors/text_to_layout_processor.py
layout_prompter/transforms/__init__.py
layout_prompter/transforms/base.py
layout_prompter/transforms/discretize_bboxes.py
layout_prompter/transforms/label_dict_sort.py
layout_prompter/transforms/lexicographic_sort.py
layout_prompter/transforms/saliency_map_to_bboxes.py
layout_prompter/transforms/shuffle_elements.py
layout_prompter/utils/__init__.py
layout_prompter/utils/bbox.py
layout_prompter/utils/configuration.py
layout_prompter/utils/image.py
layout_prompter/utils/metrics.py
layout_prompter/utils/testing.py
layout_prompter/utils/workers.py
layout_prompter/visualizers/__init__.py
layout_prompter/visualizers/base.py
layout_prompter-0.8.0.dist-info/METADATA
layout_prompter-0.8.0.dist-info/WHEEL
layout_prompter-0.8.0.dist-info/licenses/LICENSE
layout_prompter-0.8.0.dist-info/RECORD
